{"assets/icons/Documents.svg":["assets/icons/Documents.svg"],"assets/icons/Figma_file.svg":["assets/icons/Figma_file.svg"],"assets/icons/Search.svg":["assets/icons/Search.svg"],"assets/icons/account.svg":["assets/icons/account.svg"],"assets/icons/bbps.png":["assets/icons/bbps.png"],"assets/icons/bharatconnect.svg":["assets/icons/bharatconnect.svg"],"assets/icons/broadband.png":["assets/icons/broadband.png"],"assets/icons/club.png":["assets/icons/club.png"],"assets/icons/credit.png":["assets/icons/credit.png"],"assets/icons/deposit.png":["assets/icons/deposit.png"],"assets/icons/doc_file.svg":["assets/icons/doc_file.svg"],"assets/icons/drop_box.svg":["assets/icons/drop_box.svg"],"assets/icons/dth.png":["assets/icons/dth.png"],"assets/icons/electricity.png":["assets/icons/electricity.png"],"assets/icons/excel_file.svg":["assets/icons/excel_file.svg"],"assets/icons/fastag.png":["assets/icons/fastag.png"],"assets/icons/folder.svg":["assets/icons/folder.svg"],"assets/icons/gas.png":["assets/icons/gas.png"],"assets/icons/google_drive.svg":["assets/icons/google_drive.svg"],"assets/icons/hospital.png":["assets/icons/hospital.png"],"assets/icons/insurance.png":["assets/icons/insurance.png"],"assets/icons/loan.png":["assets/icons/loan.png"],"assets/icons/logo.svg":["assets/icons/logo.svg"],"assets/icons/media.svg":["assets/icons/media.svg"],"assets/icons/media_file.svg":["assets/icons/media_file.svg"],"assets/icons/menu_dashboard.svg":["assets/icons/menu_dashboard.svg"],"assets/icons/menu_doc.svg":["assets/icons/menu_doc.svg"],"assets/icons/menu_notification.svg":["assets/icons/menu_notification.svg"],"assets/icons/menu_profile.svg":["assets/icons/menu_profile.svg"],"assets/icons/menu_setting.svg":["assets/icons/menu_setting.svg"],"assets/icons/menu_store.svg":["assets/icons/menu_store.svg"],"assets/icons/menu_task.svg":["assets/icons/menu_task.svg"],"assets/icons/menu_tran.svg":["assets/icons/menu_tran.svg"],"assets/icons/mobile.jpg":["assets/icons/mobile.jpg"],"assets/icons/municipal.png":["assets/icons/municipal.png"],"assets/icons/one_drive.svg":["assets/icons/one_drive.svg"],"assets/icons/pdf_file.svg":["assets/icons/pdf_file.svg"],"assets/icons/rent.png":["assets/icons/rent.png"],"assets/icons/society.png":["assets/icons/society.png"],"assets/icons/sound_file.svg":["assets/icons/sound_file.svg"],"assets/icons/tax.png":["assets/icons/tax.png"],"assets/icons/telephone.png":["assets/icons/telephone.png"],"assets/icons/tv.png":["assets/icons/tv.png"],"assets/icons/unknown.svg":["assets/icons/unknown.svg"],"assets/icons/water.png":["assets/icons/water.png"],"assets/icons/xd_file.svg":["assets/icons/xd_file.svg"],"assets/images/confirm.json":["assets/images/confirm.json"],"assets/images/login1.png":["assets/images/login1.png"],"assets/images/logo.png":["assets/images/logo.png"],"assets/images/payout.png":["assets/images/payout.png"],"assets/images/profile_pic.png":["assets/images/profile_pic.png"],"packages/cupertino_icons/assets/CupertinoIcons.ttf":["packages/cupertino_icons/assets/CupertinoIcons.ttf"]}